coco2yolo_kaggle/__init__.py
coco2yolo_kaggle/cli.py
coco2yolo_kaggle/file_utils.py
coco2yolo_kaggle/general_json2yolo.py
coco2yolo_kaggle-0.2.1.dist-info/licenses/LICENSE
coco2yolo_kaggle-0.2.1.dist-info/METADATA
coco2yolo_kaggle-0.2.1.dist-info/WHEEL
coco2yolo_kaggle-0.2.1.dist-info/entry_points.txt
coco2yolo_kaggle-0.2.1.dist-info/top_level.txt
coco2yolo_kaggle-0.2.1.dist-info/RECORD
