Metadata-Version: 2.4
Name: coco2yolo-kaggle
Version: 0.2.1
Summary: Convert COCO dataset to YOLO format in Kaggle environment
Author-email: Steven Chen <i@stevenchen.site>
License: MIT
Project-URL: Homepage, https://github.com/StevenChen16/coco2yolo_kaggle
Project-URL: Issues, https://github.com/StevenChen16/coco2yolo_kaggle/issues
Classifier: Programming Language :: Python :: 3
Classifier: License :: OSI Approved :: MIT License
Classifier: Operating System :: OS Independent
Requires-Python: >=3.6
License-File: LICENSE
Requires-Dist: numpy
Requires-Dist: tqdm
Requires-Dist: pillow
Requires-Dist: pandas
Dynamic: license-file
